LICENSE
MANIFEST.in
README-pypi.md
README.md
pyproject.toml
blempy/__init__.py
blempy.egg-info/PKG-INFO
blempy.egg-info/SOURCES.txt
blempy.egg-info/dependency_links.txt
blempy.egg-info/top_level.txt