Metadata-Version: 2.4
Name: blempy
Version: 0.5.0
Summary: A small example package
Author-email: varkenvarken <author@example.com>
License-Expression: GPL-3.0-or-later
Project-URL: Homepage, https://github.com/varkenvarken/blempy
Project-URL: Issues, https://github.com/varkenvarken/blempy/issues
Classifier: Development Status :: 4 - Beta
Classifier: Programming Language :: Python :: 3.11
Classifier: Operating System :: OS Independent
Requires-Python: >=3.11
License-File: LICENSE
Dynamic: license-file
